LICENSE
MANIFEST.in
README.rst
gcs_signurl.py
setup.py
gcs_signurl.egg-info/PKG-INFO
gcs_signurl.egg-info/SOURCES.txt
gcs_signurl.egg-info/dependency_links.txt
gcs_signurl.egg-info/entry_points.txt
gcs_signurl.egg-info/requires.txt
gcs_signurl.egg-info/top_level.txt