Metadata-Version: 1.1
Name: gcs-signurl
Version: 0.0.2
Summary: Google Cloud Storage URL signer that supports looong expiration dates
Home-page: https://github.com/haizaar/gcr-signer
Author: Zaar Hai
Author-email: haizaar@haizaar.com
License:                                  Apache License
